README.md
setup.py
python_simple_google_maps.egg-info/PKG-INFO
python_simple_google_maps.egg-info/SOURCES.txt
python_simple_google_maps.egg-info/dependency_links.txt
python_simple_google_maps.egg-info/not-zip-safe
python_simple_google_maps.egg-info/requires.txt
python_simple_google_maps.egg-info/top_level.txt
simple_google_maps/__init__.py