Metadata-Version: 1.0
Name: python-simple-google-maps
Version: 0.0.2
Summary: Simple Python google maps generator
Home-page: https://github.com/remaudcorentin-dev/python-simple-google-maps
Author: Corentin Remaud
Author-email: remaudcorentin.dev@gmail.com
License: MIT
Platform: UNKNOWN
